szn/__init__.py
szn/videoportal/__init__.py
szn/videoportal/markdown_extended.py
szn_videoportal_commn-0.2.dist-info/METADATA
szn_videoportal_commn-0.2.dist-info/WHEEL
szn_videoportal_commn-0.2.dist-info/top_level.txt
szn_videoportal_commn-0.2.dist-info/RECORD
