Metadata-Version: 2.1
Name: szn-videoportal-commn
Version: 0.2
Summary: Package contains shared and handy tools for all our projects.
Maintainer: Ondrej Gersl
Maintainer-email: ondra.gersl@seznam.cz
Classifier: Development Status :: 5 - Production/Stable
Classifier: Programming Language :: Python :: 3
Classifier: Topic :: Database
Requires-Dist: requests
